pyenerginet/__init__.py
pyenerginet/base.py
pyenerginet/data.py
pyenerginet-0.4.dist-info/METADATA
pyenerginet-0.4.dist-info/WHEEL
pyenerginet-0.4.dist-info/licenses/LICENSE
pyenerginet-0.4.dist-info/RECORD
