Metadata-Version: 2.4
Name: pyenerginet
Version: 0.4
Summary: A package to extract data from Energinet and Energi Data Service
Project-URL: Homepage, https://github.com/edu230991/pyenerginet
Project-URL: Issues, https://github.com/edu230991/pyenerginet/issues
Author-email: Edoardo Simioni <edu230991@gmail.com>
License-File: LICENSE
Classifier: Operating System :: OS Independent
Classifier: Programming Language :: Python :: 3
Requires-Python: >=3.9
Requires-Dist: numpy<1.27,>=1.26.4
Requires-Dist: pandas<2.3,>=2.2.1
Requires-Dist: requests-cache<2,>=1.2.1
Requires-Dist: requests<2.32,>=2.31.0
